Workbook

Sheet Company Performance
A1: Metric ($M) | B1: FY2024 | C1: FY2025 | D1: FY2026
A2: Subscription Revenue | B2: 2205 | C2: 2556 | D2: 2855
A3: Professional Services & Other | B3: 58 | C3: 54 | D3: 64
A4: Total Revenue | B4: 2263 | C4: 2610 | D4: 2919
A5: Total Cost of Revenue | B5: 581 | C5: 618 | D5: 661
A6: Gross Profit | B6: 1682 | C6: 1992 | D6: 2258
A7: R&D | B7: 656 | C7: 642 | D7: 639
A8: Sales & Marketing | B8: 1036 | C8: 965 | D8: 1018
A9: G&A | B9: 450 | C9: 448 | D9: 448
A10: Restructuring & Other | B10: 56 | C10: 11 | D10: 4
A11: Total Operating Expenses | B11: 2198 | C11: 2066 | D11: 2109
A12: Operating Income (Loss) | B12: -516 | C12: -74 | D12: 149
A13: Net Income (Loss) | B13: -355 | C13: 28 | D13: 235
A18: Calculated Metric | B18: FY2024 | C18: FY2025 | D18: FY2026
A19: Revenue Growth % | C19: =(C4-B4)/B4 -> 0.15333628 | D19: =(D4-C4)/C4 -> 0.1183908
A20: Gross Margin % | B20: =B6/B4 -> 0.74326116 | C20: =C6/C4 -> 0.76321839 | D20: =D6/D4 -> 0.77355259
A21: Operating Margin % | B21: =B12/B4 -> -0.22801591 | C21: =C12/C4 -> -0.02835249 | D21: =D12/D4 -> 0.051044878
A22: Operating Expense % of Revenue | B22: =B11/B4 -> 0.97127707 | C22: =C11/C4 -> 0.79157088 | D22: =D11/D4 -> 0.72250771
A23: Net Margin % | B23: =B13/B4 -> -0.15687141 | C23: =C13/C4 -> 0.010727969 | D23: =D13/D4 -> 0.080507023
A26: Expense Metric | B26: FY2024 | C26: FY2025 | D26: FY2026
A27: R&D % of Revenue | B27: =B7/B4 -> 0.28988069 | C27: =C7/C4 -> 0.24597701 | D27: =D7/D4 -> 0.21891059
A28: Sales & Marketing % of Revenue | B28: =B8/B4 -> 0.45779938 | C28: =C8/C4 -> 0.3697318 | D28: =D8/D4 -> 0.34874957
A29: G&A % of Revenue | B29: =B9/B4 -> 0.19885108 | C29: =C9/C4 -> 0.17164751 | D29: =D9/D4 -> 0.15347722

Sheet Business Drivers 
A1: Business Driver | B1: Evidence | C1: Why It Matters | D1: Consulting Implication
A2: Revenue Growth | B2: FY26 revenue increased 12% to $2.919B | C2: Business continues to scale | D2: Operating model must support growth without proportional cost growth
A3: Customer Expansion | B3: Growth came from new customers plus additional solutions sold to existing customers; DBNRR was 106% | C3: Growth depends on both acquisition and expansion | D3: Cross-functional coordination across sales, product and customer success becomes important
A4: Improved Cost Efficiency | B4: Operating expenses declined from 97% of revenue in FY24 to 72% in FY26 | C4: Okta is demonstrating operating leverage | D4: Opportunity shifts from aggressive cost cutting toward sustaining efficiency
A5: Partner Ecosystem Shift | B5: Okta expects professional-services revenue to decline as more engagements shift to partners beginning FY27 | C5: Work is moving outside the organization | D5: Requires clear partner governance, accountability and service-delivery standards
A6: Organizational Restructuring | B6: Restructuring charges declined from $56M in FY24 to $4M in FY26 | C6: Okta has already undergone organizational changes | D6: Future-state operating model should institutionalize efficiency gains rather than rely on recurring restructuring
A7: Workforce Growth Resumed | B7: Employees increased from 5,914 to 6,366 in FY26 | C7: Okta is adding organizational capacity again | D7: Growth creates a need to preserve productivity and prevent organizational complexity
A8: Workforce Globalization | B8: International workforce increased from 33% to 44% of employees between FY24–FY26 | C8: Organization is becoming increasingly global | D8: Governance, processes and decision rights must work across geographies
A9: Enterprise Customer Growth | B9: Customers >$100K ACV increased from 4,485 to 5,100 | C9: Larger customers create greater revenue opportunity but potentially greater service complexity | D9: Operating model must support increasingly complex enterprise relationships

Sheet Operational Metrics
A1: Metric | B1: FY2024 | C1: FY2025 | D1: FY2026
A2: Employees | B2: 5908 | C2: 5914 | D2: 6366
A3: Total Customers | B3: 18950 | C3: 19650 | D3: 20,000+
A4: Customers >$100K ACV | B4: 4485 | C4: 4800 | D4: 5100
A5: International Employees | B5: 0.33 | C5: 0.38 | D5: 0.44
A6: U.S. Employees | B6: 0.67 | C6: 0.62 | D6: 0.56
A7: Integrations | B7: 7,000+ | C7: 7,000+ | D7: 7,000+
A10: Calculated Metric | B10: FY2024 | C10: FY2025 | D10: FY2026
A11: Employee Growth | C11: =(C2-B2)/B2 -> 0.0010155721 | D11: =(D2-C2)/C2 -> 0.076428813
A12: Revenue per Employee ($M) | B12: ='Company Performance'!B4/'Operational Metrics'!B2 -> 0.38303995 | C12: ='Company Performance'!C4/'Operational Metrics'!C2 -> 0.44132567 | D12: ='Company Performance'!D4/'Operational Metrics'!D2 -> 0.45852969
A13: Large Customer %
B16: ='Operational Metrics'!B8/'Operational Metrics'!B6 -> 0 | C16: ='Operational Metrics'!C8/'Operational Metrics'!C6 -> 0 | D16: ='Operational Metrics'!D8/'Operational Metrics'!D6 -> 0
